score.http-0.5.6-py3.7-nspkg.pth
score/http/__init__.py
score/http/_conf.py
score/http/_init.py
score/http/_urltpl.py
score.http-0.5.6.dist-info/COPYING.LESSER.txt
score.http-0.5.6.dist-info/METADATA
score.http-0.5.6.dist-info/WHEEL
score.http-0.5.6.dist-info/namespace_packages.txt
score.http-0.5.6.dist-info/top_level.txt
score.http-0.5.6.dist-info/RECORD
